setup.cfg
setup.py
edx_shopify/__init__.py
edx_shopify/admin.py
edx_shopify/models.py
edx_shopify/tasks.py
edx_shopify/urls.py
edx_shopify/utils.py
edx_shopify/views.py
edx_shopify.egg-info/PKG-INFO
edx_shopify.egg-info/SOURCES.txt
edx_shopify.egg-info/dependency_links.txt
edx_shopify.egg-info/top_level.txt
edx_shopify/migrations/0001_initial.py
edx_shopify/migrations/__init__.py
tests/__init__.py
tests/test_models.py
tests/test_tasks.py
tests/test_utils.py
tests/test_views.py