Metadata-Version: 1.1
Name: edx-shopify
Version: 0.0.2
Summary: edX Shopify: integrates Open edX with Shopify
Home-page: https://github.com/hastexo/edx-shopify
Author: hastexo
Author-email: pypi@hastexo.com
License: AGPL-3.0
Platform: UNKNOWN
Classifier: Development Status :: 3 - Alpha
Classifier: Framework :: Django
Classifier: Intended Audience :: Education
Classifier: License :: OSI Approved :: GNU Affero General Public License v3
Classifier: Operating System :: POSIX :: Linux
Classifier: Programming Language :: Python
Classifier: Topic :: Education :: Computer Aided Instruction (CAI)
Classifier: Topic :: Education
